addition_library/__init__.py
addition_library/addition.py
Addition_Library-0.1.0.dist-info/METADATA
Addition_Library-0.1.0.dist-info/WHEEL
Addition_Library-0.1.0.dist-info/top_level.txt
Addition_Library-0.1.0.dist-info/RECORD
